turkish_lm_tuner/__init__.py
turkish_lm_tuner/dataset_processor.py
turkish_lm_tuner/evaluator.py
turkish_lm_tuner/metrics.py
turkish_lm_tuner/t5_classifier.py
turkish_lm_tuner/tr_datasets.py
turkish_lm_tuner/trainer.py
turkish_lm_tuner-1.dist-info/LICENSE
turkish_lm_tuner-1.dist-info/METADATA
turkish_lm_tuner-1.dist-info/WHEEL
turkish_lm_tuner-1.dist-info/top_level.txt
turkish_lm_tuner-1.dist-info/RECORD
