Metadata-Version: 2.1
Name: turkish-lm-tuner
Version: 1
Summary: Implementation of the Turkish LM Tuner
Author-email: Gökçe Uludoğan <gokceuludogan@gmail.com>, Zeynep Yirmibeşoğlu Balal <yirmibesogluz@gmail.com>, Furkan Akkurt <furkanakkurt9285@gmail.com>
License: Apache-2.0
Project-URL: Source Code, https://github.com/boun-tabi-LMG/turkish-lm-tuner
Project-URL: Bug Tracker, https://github.com/boun-tabi-LMG/turkish-lm-tuner/issues
Project-URL: Documentation, https://turkish-lm-tuner-docs.boun-tabi-LMG.github.io/
Keywords: nlp,turkish,language models,finetuning
Classifier: Development Status :: 5 - Production/Stable
Classifier: Intended Audience :: Developers
Classifier: Intended Audience :: Science/Research
Classifier: Topic :: Scientific/Engineering :: Artificial Intelligence
Classifier: Topic :: Scientific/Engineering :: Information Analysis
Classifier: Natural Language :: Turkish
Classifier: Operating System :: OS Independent
Classifier: Programming Language :: Python
Classifier: Programming Language :: Python :: 3
Classifier: Programming Language :: Python :: 3.9
Classifier: Programming Language :: Python :: 3.9
Classifier: Programming Language :: Python :: 3.10
Classifier: Programming Language :: Python :: 3.11
Requires-Python: >=3.9
License-File: LICENSE
Requires-Dist: tqdm
Requires-Dist: hydra-core
Requires-Dist: numpy
Requires-Dist: pandas
Requires-Dist: scikit-learn
Requires-Dist: torch >=2.0
Requires-Dist: transformers >=4.35
Requires-Dist: datasets
Requires-Dist: tokenizers
Requires-Dist: sentencepiece
Requires-Dist: accelerate
Requires-Dist: safetensors
Requires-Dist: evaluate
Requires-Dist: wandb
Requires-Dist: huggingface-hub
Requires-Dist: absl-py
Requires-Dist: rouge-score
Requires-Dist: sacrebleu
Requires-Dist: seqeval
